bounded_iterator.py
bounded_iterator-1.0.2.dist-info/LICENSE
bounded_iterator-1.0.2.dist-info/METADATA
bounded_iterator-1.0.2.dist-info/WHEEL
bounded_iterator-1.0.2.dist-info/top_level.txt
bounded_iterator-1.0.2.dist-info/zip-safe
bounded_iterator-1.0.2.dist-info/RECORD
