Metadata-Version: 2.1
Name: bounded-iterator
Version: 1.0.2
Summary: Limits the number of values generated by an iterator until acknowledged.
Home-page: https://github.com/jruere/bounded-iterator
Author: Javier Ruere
Author-email: javier@ruere.com.ar
License: LGPLv3
Keywords: concurrency parallelism iterator iterable multiprocessing imap
Platform: UNKNOWN
Classifier: Development Status :: 5 - Production/Stable
Classifier: Intended Audience :: Developers
Classifier: License :: OSI Approved :: GNU Lesser General Public License v3 or later (LGPLv3+)
Classifier: Programming Language :: Python :: 3
Classifier: Programming Language :: Python :: 3.6
Classifier: Programming Language :: Python :: 3.7
Classifier: Programming Language :: Python :: 3.8
Classifier: Programming Language :: Python :: 3.9
Classifier: Programming Language :: Python :: 3.10
Classifier: Programming Language :: Python :: Implementation :: CPython
Classifier: Programming Language :: Python :: Implementation :: PyPy
Classifier: Topic :: Software Development :: Libraries :: Python Modules
License-File: LICENSE
